autosend/__init__.py
autosend/autosend.py
autosend-0.0.5.dist-info/LICENSE
autosend-0.0.5.dist-info/METADATA
autosend-0.0.5.dist-info/WHEEL
autosend-0.0.5.dist-info/top_level.txt
autosend-0.0.5.dist-info/RECORD
