Metadata-Version: 2.1
Name: autosend
Version: 0.0.5
Summary: a simple tool that logs what is printed on the screen, and emails the logs to you
Home-page: https://github.com/flishwang/autosend
Author: flish_wang
Author-email: flish_wang@sina.com
Classifier: Development Status :: 3 - Alpha
Classifier: Programming Language :: Python :: 3
Classifier: License :: OSI Approved :: MIT License
Classifier: Operating System :: OS Independent
Requires-Python: >=3
License-File: LICENSE
Requires-Dist: pyyaml
